MANIFEST.in
README.rst
setup.cfg
setup.py
examples/__init__.py
examples/boston_price_prediction.py
examples/gradient_descent_optimizations.py
examples/hamming_network.py
examples/plots.py
examples/pnn.py
examples/sofm.py
neural_python.egg-info/PKG-INFO
neural_python.egg-info/SOURCES.txt
neural_python.egg-info/dependency_links.txt
neural_python.egg-info/entry_points.txt
neural_python.egg-info/not-zip-safe
neural_python.egg-info/requires.txt
neural_python.egg-info/top_level.txt
neuralpy/__init__.py
neuralpy/algorithms/__init__.py
neuralpy/algorithms/feedforward.py
neuralpy/algorithms/utils.py
neuralpy/algorithms/associative/__init__.py
neuralpy/algorithms/associative/base.py
neuralpy/algorithms/associative/hebb.py
neuralpy/algorithms/associative/instar.py
neuralpy/algorithms/associative/kohonen.py
neuralpy/algorithms/associative/oja.py
neuralpy/algorithms/backprop/__init__.py
neuralpy/algorithms/backprop/backpropagation.py
neuralpy/algorithms/backprop/conjugate_gradient.py
neuralpy/algorithms/backprop/gradient_descent.py
neuralpy/algorithms/backprop/hessian_diagonal.py
neuralpy/algorithms/backprop/levenberg_marquardt.py
neuralpy/algorithms/backprop/momentum.py
neuralpy/algorithms/backprop/quasi_newton.py
neuralpy/algorithms/backprop/quickprop.py
neuralpy/algorithms/backprop/rprop.py
neuralpy/algorithms/backprop/steps/__init__.py
neuralpy/algorithms/backprop/steps/base.py
neuralpy/algorithms/backprop/steps/delta_bar_delta.py
neuralpy/algorithms/backprop/steps/error_difference_update.py
neuralpy/algorithms/backprop/steps/leak_step.py
neuralpy/algorithms/backprop/steps/linear_search.py
neuralpy/algorithms/backprop/steps/search_then_converge.py
neuralpy/algorithms/backprop/steps/simple_step_minimization.py
neuralpy/algorithms/backprop/steps/wolfe_search.py
neuralpy/algorithms/backprop/weights/__init__.py
neuralpy/algorithms/backprop/weights/base.py
neuralpy/algorithms/backprop/weights/weight_decay.py
neuralpy/algorithms/backprop/weights/weight_elimination.py
neuralpy/algorithms/basics/__init__.py
neuralpy/algorithms/basics/base.py
neuralpy/algorithms/basics/lms.py
neuralpy/algorithms/basics/modify_relaxation.py
neuralpy/algorithms/basics/perceptron.py
neuralpy/algorithms/competitive/__init__.py
