Metadata-Version: 1.1
Name: neural-python
Version: 0.0.7
Summary: 
